README.md
setup.py
sumbeanDay01/__init__.py
sumbeanDay01/astro.py
sumbeanDay01/cgs.py
sumbeanDay01/cosmocalc.py
sumbeanDay01/fs.py
sumbeanDay01/grb.py
sumbeanDay01/rs.py
sumbeanDay01.egg-info/PKG-INFO
sumbeanDay01.egg-info/SOURCES.txt
sumbeanDay01.egg-info/dependency_links.txt
sumbeanDay01.egg-info/top_level.txt
test/test.py
test/test01.py