Metadata-Version: 2.1
Name: sumbeanDay01
Version: 0.0.4
Summary: 测试
Author: sumbean
Author-email: 1041267952@qq.com
